README.rst
setup.py
gunicorn_websocket.egg-info/PKG-INFO
gunicorn_websocket.egg-info/SOURCES.txt
gunicorn_websocket.egg-info/dependency_links.txt
gunicorn_websocket.egg-info/requires.txt
gunicorn_websocket.egg-info/top_level.txt
gunicornwebsocket/__init__.py
gunicornwebsocket/exceptions.py
gunicornwebsocket/handler.py
gunicornwebsocket/python_fixes.py
gunicornwebsocket/websocket.py