Metadata-Version: 1.0
Name: gunicorn-websocket
Version: 0.0.1
Summary: Websocket handler for the gunicorn server, a Python wsgi server, fork and modify from gevent-websocket
Home-page: http://code.dapps.douban.com/gunicorn-websocket
Author: CMGS
Author-email: ilskdw@gmail.com
License: BSD
Platform: UNKNOWN
Classifier: Development Status :: 4 - Beta
Classifier: License :: OSI Approved :: BSD License
Classifier: Programming Language :: Python
Classifier: Operating System :: MacOS :: MacOS X
Classifier: Operating System :: POSIX
Classifier: Topic :: Internet
Classifier: Topic :: Software Development :: Libraries :: Python Modules
Classifier: Intended Audience :: Developers
